{
  "ok": true,
  "sourceUrl": "https://comfandisa-my.sharepoint.com/personal/94060845_comfandi_com_co/_layouts/15/onedrive.aspx?id=%2Fpersonal%2F94060845%5Fcomfandi%5Fcom%5Fco%2FDocuments%2FSEGUIMIENTO%20A%20FM%20JUNIO%202026%20contingencia%2F01%2DCONTROL%20MTTO%20PREVE%2DCRON%202026&viewid=90654f3d%2D4e0e%2D4877%2D9258%2D8cbdaa8ef499&ga=1",
  "requestedPeriod": "2026/06-JUNIO",
  "inputFolderPath": "/personal/94060845_comfandi_com_co/Documents/SEGUIMIENTO A FM JUNIO 2026 contingencia/01-CONTROL MTTO PREVE-CRON 2026",
  "scopedFolderPath": "/personal/94060845_comfandi_com_co/Documents/SEGUIMIENTO A FM JUNIO 2026 contingencia/01-CONTROL MTTO PREVE-CRON 2026/2026/06-JUNIO/SOPORTE DE VISITAS",
  "totalFilesRead": 52,
  "pdfFilesRead": 52,
  "ignoredNonPdf": 0,
  "folders": [
    {
      "path": "/personal/94060845_comfandi_com_co/Documents/SEGUIMIENTO A FM JUNIO 2026 contingencia/01-CONTROL MTTO PREVE-CRON 2026/2026/06-JUNIO/SOPORTE DE VISITAS",
      "depth": 0,
      "files": [],
      "folders": [
        "ZONA SUR",
        "ZONA NORTE",
        "VALLE 1"
      ],
      "errors": []
    },
    {
      "path": "/personal/94060845_comfandi_com_co/Documents/SEGUIMIENTO A FM JUNIO 2026 contingencia/01-CONTROL MTTO PREVE-CRON 2026/2026/06-JUNIO/SOPORTE DE VISITAS/ZONA SUR",
      "depth": 1,
      "files": [
        "09-Drogueria Morichal.pdf",
        "17-Drogueria Valle del Lili II.pdf",
        "15-Drogueria Unicentro.pdf",
        "16-Drogueria Valle del Lili.pdf",
        "01-Centro Campestre Comfandi Pance ( 16 A 20) por indice digital.pdf",
        "11- Drogueria San Fernando.pdf",
        "01-Centro Campestre Comfandi Pance ( 09 A 13) por indice digital.pdf",
        "04-Drogueria Cañas Gordas.pdf",
        "18-Ips Comfandi Morichal ( 01 A 10) por firma de gestor.pdf",
        "14-Drogueria Tequendama II.pdf",
        "02-Clinica Comfandi Tequendama ( 09 A 13 ) .pdf",
        "13-Drogueria Supermercado Cosmocentro.pdf",
        "10-Drogueria Podium.pdf",
        "07-Drogueria Clinica Vida.pdf",
        "08-Drogueria Cll 25 EDS Caney.pdf",
        "06-Drogueria Cerros Plaza.pdf",
        "19- Ips Salud Integral Amiga (11 A 17 ).pdf",
        "05-Droguería Cañaveralejo.pdf",
        "02-Clinica Comfandi Tequendama ( 01 A 06 ).pdf",
        "01-Centro Campestre Comfandi Pance ( 01 A 06) por indice digital.pdf",
        "12-Drogueria San Joaquín.pdf"
      ],
      "folders": [],
      "errors": []
    },
    {
      "path": "/personal/94060845_comfandi_com_co/Documents/SEGUIMIENTO A FM JUNIO 2026 contingencia/01-CONTROL MTTO PREVE-CRON 2026/2026/06-JUNIO/SOPORTE DE VISITAS/ZONA NORTE",
      "depth": 1,
      "files": [
        "18- Ips Comfandi Alameda (01 A 11 ) por indice digital.pdf",
        "05-Colegio Yumbo (01 A 05 )por indice digital.pdf",
        "04-Centro Campestre Comfandi Arroyohondo ( 09 A 13 )por firma indice digital (1).pdf",
        "06-Ips Comfandi Torres ( 16 A 20 )POR INDICE DIG.pdf",
        "21-Campus E Centro (Fomento Piso 3) 12 -13 por firmas .pdf",
        "02- Colegio El Prado Sede Bachillerato ( 09 A 12 )por firma de índice digital.pdf",
        "05-Colegio Yumbo (09 A 13 )por indice digital.pdf",
        "02- Colegio El Prado Sede Bachillerato ( 01 A 05 )por firma de índice digital.pdf",
        "03- Ips Comfandi El Prado ( 09 A 13 )por firma de gestor e indice digital.pdf",
        "03- Ips Comfandi El Prado ( 01 A 06 )por firma de gestor e indice digital.pdf",
        "15-Ips Comfandi Yumbo ( 01 A 11 ).pdf",
        "20-Campus E Centro ( 01 A 11 )por firma e ind digital.pdf",
        "06-Ips Comfandi Torres ( 09 A 13 ) por indice digital.pdf",
        "01- Edificio Comfandi El Prado ( 01 A 06 )por firma de gestor e indice digital.pdf",
        "04-Centro Campestre Comfandi Arroyohondo ( 16 A 20 ).por firma indice dig..pdf",
        "04- Centro Campestre Comfandi Arroyohondo ( 01 A 06 ) por firma índice digital.pdf",
        "06- Ips Comfandi Torres ( 01 A 06 ) Por indice digital.pdf",
        "01-Edificio Comfandi El Prado ( 09 A 13 )por firma e indice digital.pdf",
        "01- Edificio Comfandi El Prado ( 16 A 20) por firma e indice.pdf"
      ],
      "folders": [],
      "errors": []
    },
    {
      "path": "/personal/94060845_comfandi_com_co/Documents/SEGUIMIENTO A FM JUNIO 2026 contingencia/01-CONTROL MTTO PREVE-CRON 2026/2026/06-JUNIO/SOPORTE DE VISITAS/VALLE 1",
      "depth": 1,
      "files": [
        "10- Clinica Comfandi Cartago ( 09 A 13 )por firma de INC digital.pdf",
        "05-Agencia de Gestión y Colocación de Empleo Buenaventura (22 A 25 ) por indice digital.pdf",
        "32- Colegio Palmira ( 01 A 05-09-10 )por firma e inc digital.pdf",
        "06-CIS Buenaventura ( 19-20 ) por indice de satisfaccion.pdf",
        "04-IETDH Buenaventura ( 01 A 18 )por indice digital.pdf",
        "08-Colegio El Lago ( 01 A 06 ).pdf",
        "01- Colegio Buga (01 A 06 ).pdf",
        "10-Clinica Comfandi Cartago ( 01 A 06 ) por indice digital.pdf",
        "17-Centro Recreativo Buga (01 05-09-10)por firma e ind digital.pdf",
        "01- Colegio Buga ( 09 A 13) por firma indice digital.pdf",
        "13- Drogueria Buga Principal (por indice digital ).pdf",
        "11-Clinica e IPS Comfandi Palmira (01 A 06 )por indice digital.pdf"
      ],
      "folders": [],
      "errors": []
    }
  ]
}